KoronaScript/Configuration.py
KoronaScript/KoronaModule.py
KoronaScript/Modules.py
KoronaScript/__init__.py
koronascript-0.2.1.dist-info/METADATA
koronascript-0.2.1.dist-info/WHEEL
koronascript-0.2.1.dist-info/top_level.txt
koronascript-0.2.1.dist-info/RECORD
