Metadata-Version: 2.1
Name: koronascript
Version: 0.2.1
Summary: Wrapper around Korona modules for processing echosounder data
Home-page: https://github.com/CRIMAC-WP4-Machine-learning/CRIMAC-KoronaScript
Author: Ketil Malde
Author-email: ketil@malde.org
